kinertia/__init__.py
kinertia/setup.py
kinertia/supervised.py
kinertia/unsupervised.py
k_inertia-1.0.0.dist-info/LICENSE
k_inertia-1.0.0.dist-info/METADATA
k_inertia-1.0.0.dist-info/WHEEL
k_inertia-1.0.0.dist-info/top_level.txt
k_inertia-1.0.0.dist-info/RECORD
