Metadata-Version: 2.1
Name: k-inertia
Version: 1.0.0
Summary: K-Inertia: A User-Friendly Machine Learning Library K-Inertia or Kavish Inertia is a Python machine learning library designed for simplicity and ease of use. With a focus on user-friendly interfaces, K-Inertia provides implementations of various machine learning algorithms, including regression, logistic regression, k-nearest neighbors, naive Bayes, support vector machines, and k-means clustering.
Home-page: 
Author: Kavish Tomar
Author-email: kavishtomar2@gmail.com
License: MIT
Keywords: machine learning,k_inertia,k-inertia,learning,ai,AI,ml,ML,K-Inertia,Machine Learning
Classifier: Development Status :: 5 - Production/Stable
Classifier: Intended Audience :: Developers
Classifier: Operating System :: OS Independent
Classifier: License :: OSI Approved :: MIT License
Classifier: Programming Language :: Python :: 3
License-File: LICENSE
Requires-Dist: numpy
